logan_iq/__init__.py
logan_iq/__main__.py
logan_iq/__version__.py
logan_iq/cli/__init__.py
logan_iq/cli/commands.py
logan_iq/cli/interactive.py
logan_iq/core/__init__.py
logan_iq/core/analyzer.py
logan_iq/core/config.py
logan_iq/core/exporter.py
logan_iq/core/filter.py
logan_iq/core/parser.py
logan_iq/core/summarizer.py
logan_iq/core/utils/__init__.py
logan_iq/core/utils/date.py
logan_iq/core/utils/string.py
logan_iq/core/utils/terminal.py
logan_iq-1.2.3.dist-info/licenses/LICENSE
tests/__init__.py
tests/test_config.py
tests/test_exporter.py
tests/test_filter.py
tests/test_parser.py
tests/test_summary.py
tests/sample_data/log_entries.py
logan_iq-1.2.3.dist-info/METADATA
logan_iq-1.2.3.dist-info/WHEEL
logan_iq-1.2.3.dist-info/entry_points.txt
logan_iq-1.2.3.dist-info/top_level.txt
logan_iq-1.2.3.dist-info/RECORD
