Metadata-Version: 2.4
Name: logan_iq
Version: 1.2.3
Summary: Interactive CLI tool for multi-format log analysis, filtering and export.
Author: heisdanielade
License-Expression: MIT
Project-URL: Homepage, https://github.com/heisdanielade/cli-logan-iq
Project-URL: Issues, https://github.com/heisdanielade/cli-logan-iq/issues
Keywords: cli,logs,analysis
Classifier: Programming Language :: Python :: 3
Classifier: Programming Language :: Python :: 3 :: Only
Classifier: Programming Language :: Python :: 3.9
Classifier: Programming Language :: Python :: 3.10
Classifier: Programming Language :: Python :: 3.11
Classifier: Operating System :: OS Independent
Classifier: Environment :: Console
Requires-Python: >=3.9
License-File: LICENSE
Requires-Dist: typer==0.16.0
Requires-Dist: tabulate==0.9.0
Requires-Dist: pytest>=7.0.0
Requires-Dist: pyfiglet>=0.8.post1
Requires-Dist: colorama>=0.4.6
Dynamic: license-file
